<expertise xmlns="xpr" xmlns:rico="rico" xmlns:xlink="http://www.w3.org/1999/xlink" xml:id="z1j1156d061" status="">
    <meta/>
    <control>
        <maintenanceStatus>new</maintenanceStatus>
        <publicationStatus/>
        <localControl localType="detailLevel">
            <term>completed</term>
        </localControl>
        <maintenanceHistory>
            <maintenanceEvent>
                <eventType>created</eventType>
                <eventDateTime standardDateTime="2021-09-13T09:37:09Z">2021-09-13T09:37:09Z</eventDateTime>
                <agentType>human</agentType>
                <agent>yplouzennec</agent>
                <eventDescription>Création de la fiche.</eventDescription>
            </maintenanceEvent>
        </maintenanceHistory>
    </control>
    <sourceDesc>
        <unitdate>1786</unitdate>
    <idno type="unitid">Z1J1156</idno>
        <idno type="item">061</idno>
        <facsimile from="0660" to="0663"/>
        <physDesc>
            <extent sketch="false">4</extent>
            
        </physDesc>
    </sourceDesc>
    <description>
        <sessions>
            <date when="1786-10-30" type="paris"/>
          <date when="1786-11-03" type="paris"/>
          <date when="1786-11-07" type="paris"/>
        </sessions>
        <places>
            <place xml:id="id4305735d81" type="paris">
                <address>
                    <street>rue Neuve Saint-Sauveur</street>
                    <buildingNumber/>
                </address>
                <complement>quartier de la Villeneuve, faisant encoignure de ladite rue et de la rue qui conduit à la cour des Miracles et de celle des Petites Vertus</complement>
                <parish/>
                
                
                <owner>Sieur Chalot</owner>
            </place>
        </places>
        <categories>
          <category type="estimation">Estimer la valeur des biens</category>
            <designation rubric="true">Visite et estimation de maison, rue Neuve Saint-Sauveur, pour le Sieur Chalot</designation>
        </categories>
        <procedure>
            <framework type="b2">L’institution est saisie dans le cadre d’une procédure (les parties nomment chacune leur expert ou un expert en commun)</framework>
            <origination type="institution">Une institution</origination>
            <sentences>
                <sentence>
                    <orgName>Conseil d'État</orgName>
                    <date when="1786-09-27"/>
                </sentence>
            </sentences>
            <case>Expropriation</case>
            <objects>
            <object type="house">Maison(s)</object>
          </objects>
        </procedure>
        <participants>
            <experts>
                <expert ref="#xpr0261" context="primary" appointment="court-appointed">
                    <title>expert des bâtiments à Paris</title>
                </expert>
            <expert ref="#xpr0228" context="primary" appointment="appointed">
                    <title>architecte expert bourgeois à Paris</title>
                </expert>
            </experts>
            <clerks>
                <clerk ref="#clrk0055">
                    <persName>
                        <surname>Bouillerot</surname>
                        <forename>Joseph</forename>
                    </persName>
                </clerk>
            </clerks>
            <parties>
                <party role="petitioner" presence="false" intervention="false">
                    <person>
                        <persName>
                            <surname/>
                            <forename/>
                        </persName>
                        <occupation>lieutenant général de Police ; désigné par le roi pour acquérir les maisons en son nom</occupation>
                    </person>
                    <status>police</status>
                    <expert ref="#xpr0261"/>
                    
                    
                </party>
            <party role="opponent" presence="true" intervention="false">
                    <person>
                        <persName>
                            <surname>Chalot</surname>
                            <forename>Louis</forename>
                        </persName>
                        <occupation>marchand de vins à Paris</occupation>
                    </person>
                    <status>owner</status>
                    <expert ref="#xpr0228"/>
                    
                    
                </party>
            </parties>
            <craftmen>
                <craftman>
                    <persName>
                        <surname/>
                        <forename/>
                    </persName>
                    <occupation/>
                </craftman>
            </craftmen>
        </participants>
        <conclusions>
            <agreement type="agreement">Accord</agreement>
            
            <opinion ref="#xpr0228 #xpr0261">"Et attention faitte à la superficie de lad[ite] maison, au quartier où elle est placée, à ce qu’elle contient de terrain en superficie, à ce que cette superficie est entièrement en bâtisse, à ce que la construction est nouvelle et en bon état, au contenu des titres et pièces dont nous avons cy dessus fait lecture, à ce que lad[ite] maison rapporte et peut rapporter de revenus, et toutes réflexions et considérations faittes, nous prisons et estimons lad[ite] maison scituée à Paris, rue neuve St Sauveur, ayant face sur la rue des Petites Vertus et sur la rue qui conduit à la cour des Miracles, et appartenante aud[it] S. Chalot, ainsy qu’elle se p[our]suit et comporte et que nous l’avons cy dessus décritte, eu égard au cours du tems présent et à la charge des dix neuf deniers parisis de cens dont elle est tenue envers l’archevêché de Paris, suivant et aux termes du contrat d’acquisition du vingt juillet mil sept cent quatre vingt cinq dont nous avons cy devant fait lecture et des droits et devoirs royaux et seigneuriaux, la somme de cinquante deux mille cinq cent livres, cy 52500₶. 
Fait par nous, expert susd[it], lesd[its] jours, mois et an […]"</opinion>
          <arrangement/>
            <estimate l="52500" s="" d=""/>
          <estimates>
                <place ref="#id4305735d81">
                    <appraisal l="52500" s="" d="">
                        <desc>Maison</desc>
                    </appraisal>
                </place>
            </estimates>
            
            <fees detail="true">
                <fee type="expert" ref="#xpr0261" l="30" s="" d=""/>
            <fee type="expert" ref="#xpr0228" l="30" s="" d=""/>
            <fee type="clerk" l="30" s="" d=""/>
            <fee type="rolls" l="36" s="" d=""/>
            <fee type="papers" l="15" s="" d=""/>
            <fee type="plans" l="" s="" d=""/>
            <fee type="prosecutors" l="" s="" d=""/>
            <fee type="help" l="" s="" d=""/>
            <fee type="other" l="3" s="" d="">Extrait</fee>
            <total l="144" s="" d=""/>
            </fees>
            <expenses mentioned="true">
            <expense type="clerk" l="31" s="10" d=""/>
            <expense type="expert" l="20" s="" d=""/>
          </expenses>
        </conclusions>
        <keywords group="estates"/>
        <keywords group="procedure">
          <term value="b6">Titre (de propriété)</term>
        </keywords>
        <keywords group="contract"/>
        <keywords group="encumbrance"/>
        <keywords group="law"/>
        <keywords group="measurement"/>
        <keywords group="repairs"/>
        <keywords group="guarantees"/>
        <keywords group="responsability"/>
        <keywords group="ownership"/>
        <keywords group="value"/>
        <keywords group="neighbourhood"/>
        <keywords group="disorder"/>
        <keywords group="transformation"/>
        <analysis/>
        <noteworthy>L'arrêt du Conseil d'État prévoit la démolition des maisons qu'il est nécessaire de supprimer pour installer la nouvelle halle à la Marée. – – – L'arrêt prévoit que faute de nomination par le propriétaire de la maison, la visite serait menée par Villetard (au nom du lieutenant général de Police) et par Duboiscerf (en son nom). Le Sieur Chalot "a choisi et nommé pour, conjointement avec nous, Villetard, fixer la valleur de lad[ite] maison, nous Poulain". – – – Les propriétaires ont été enjoints de donner congé à leurs locataires le 1er janvier 1787.</noteworthy>
    </description>
</expertise>